[{"bus_id":"H10","From":"Cold Spring Harbor - Cold Spring Harbor State Park","To":"Commack - Macy's Plaza","S_No":"1","stop_id":["Cold Spring Harbor - Cold Spring Harbor State Park","Huntington - Main St (25a) @ Nathan Hale Dr","Huntington - New York Ave (110) @ Main St (25a)","Huntington Station - Oakwood Rd @ Huntington Hs","Huntington Station - Oakwood Rd @ Pulaski Rd","Huntington Station - Pulaski @ NY Ave (110)Depot Rd","Huntington Station - Huntington LIRR Train Station (South Side)","Huntington Station - Pulaski Rd @ Park Ave","Greenlawn - Pulaski Rd @ Broadway-Greenlawn","Greenlawn - Pulaski Rd @ Paumanack Villages","East Northport - Pulaski Rd @ Larkfield Rd","East Northport - Huntington Square Mall (Sears)","Commack - Macy's Plaza"]},{"bus_id":"H20","From":"New York Ave (110) @ Park Ave","To":"Huntington LIRR (Fairground Loop)","S_No":"3","stop_id":["New York Ave (110) @ Park Ave","Huntington Hospital","Village Green Center","Park Ave @ Woodhull Rd","Huntington LIRR","Depot Rd @ E Pulaski Rd","W 11th St @ 8th Ave","Jericho Tpke & West Hills Rd","Walt Whitman Shops","Target","Depot Rd @ 17th St","Huntington LIRR (Fairground Loop)"]},{"bus_id":"H30","From":"New York Ave (110) @ Park Ave","To":"Walt Whitman Shops","S_No":"5","stop_id":["New York Ave (110) @ Park Ave","Main St (25a) @ New York Ave (110)","Main St (25a) @ Park Ave","Village Green Center","Park Circle","Broadway-Greenlawn @ Pulaski Rd","Broadway-Greenlawn @ Little Plains Rd","Broadway-Greenlawn @ E Jericho Tpk","Jericho Tpk @ Pidgeon Hill Rd/ Depot Rd","Pidgeon Hill Rd @ South Huntington Library","Wolf Hill Rd @ Pidgeon Hill Rd","Walt Whitman Shops"]},{"bus_id":"H40","From":"Va Medical Center","To":"Walt Whitman Shops","S_No":"7","stop_id":["Va Medical Center","Fort Salonga @ Main St","Main St @ Woodbine Ave","Laurel Rd @ Ft Salonga Rd (25a)","Larkfield Rd @ Pulaski Rd","Elwood Rd @ Cedar Rd","Elwood Rd @ E Jericho Tpk","Broadway-Greenlawn @ E Jericho Tpk","E Jericho Tpk @ Depot/Pidgeon Hill Rd","Walt Whitman Shops"]}]