[{"bus_id":"122","From":"Square","To":"Chorley","S_No":"1","stop_id":["Square","Highfield Farm","St Johns School","Windsor Drive","Windsor Drive","St Johns School","Sandy Lane","Highfield Farm","Blackburn Road","Fishwick Lane","Millbrook Close","Red Lion Hotel","Town Lane","St Barnabas Church","Garstang House Farm","Kittiwake Road","Motorway Bridge","Morris Road","Beaconsfield Terrace","All Seasons Leisure Centre","Millfield Road","Park Street","Booths","Chorley"]},{"bus_id":"463","From":"Guildford Avenue","To":"St Johns School","S_No":"3","stop_id":["Guildford Avenue","Merton Grove","Kittiwake Road","Four Lane Ends","St Barnabas Church","Fishwick Lane","Blackburn Road","Highfield Farm","St Johns School","St Johns School"]},{"bus_id":"585","From":"Post Office","To":"High School Grounds","S_No":"5","stop_id":["Post Office","Berry Lane","Police Station","Stone Bridge","Aldi","Halfpenny Lane","Brabiner Lane","Whittingham Hospital the Lodge","Whittingham House","Whittingham Lane West","Stags Head","The Grapes Inn","Sports Pavilion","Oakleaf Close","Langley Lane","Langley Lane","Orchard Farm","Italian Orchard","Daniels Cross","Whittingham Lane","Sunningdale","Normandy Road","Sunningdale","High School Grounds"]},{"bus_id":"812","From":"New Lane","To":"St Michaels Cehs","S_No":"7","stop_id":["New Lane","Lydiate Farm","St Marys Church","Tincklers Lane","Towngate","Lawrence Lane","Institute","Park Street","Church","Whalley Road","The Warings","Park Hall Entrance","Services West","Hinds Head","Charter Lane","Leeson Avenue","Dog And Partridge","Church Lane","Rail Station","The Talbot","Washington Lane","Southport Road","Lancashire College","Parklands Hs","Woodville Road","St Michaels Cehs"]}]