[{"bus_id":"1","From":"Mtc","To":"Mtc 2","S_No":"1","stop_id":["Mtc","N 5th St & 2nd Ave","7th & University","12th & University Wb","Salvation Army","20th & University","25th & University","Hamline & University","Christus Rex","Hancock/Bek","Wilkerson","Stanford Center","10th & Stanford","13th & Stanford","N 39th St Shelter","N 39th St & 6th Ave","Stanford & 6th Ave N","Princeton & 6th Ave N","Harvard & 6th Ave N","Hamline & 6th Ave","23rd & University","18th & University","15th & University","12th & University Eb","Ymca","Mtc 2"]},{"bus_id":"2","From":"Mtc","To":"Mtc 2","S_No":"3","stop_id":["Mtc","N 5th St & 2nd Ave","N 5th St & 7th Ave","N 5th & 10th Ave","Home Of Economy","Hugo's (N 20th St)","N 20th St & 10th Ave","N 25th St & 9th Ave","West School","Valley Middle School","St. Anne's","Winship School","N 12th St & 5th Ave","N 7th St & 5th Ave","N 4th St & 5th Ave","Central High","Mtc 2"]},{"bus_id":"3","From":"Mtc","To":"Mtc","S_No":"5","stop_id":["Mtc","1st Ave S","The Link","5th & Cherry","8th & Cherry","10th & Belmont","13th & Cherry","Lewis & Clark School","S 15th St & 13th Ave","S 17th St & 13th Ave","S 20th St & 13th Ave","13th & Rider Rd","Hugo's (13th Ave S)","Altru Columbia Rd","Red River High","S 20th St & 17th Ave","S 17th St & 17th Ave","Midtown","S 12th St & 17th Ave","S 10th St & 17th Ave","17th & Cherry","13th & Cherry Nb","10th & Cherry","6th & Cherry","4th & Cherry","Mtc"]},{"bus_id":"4","From":"Mtc","To":"Mtc","S_No":"7","stop_id":["Mtc","Cabela's","City Hall","10th & Central","17th & Central","Northland College","20th St & 5th Ave NE","17th St & 5th Ave NE","Fairfield Inn","Hugo's (East Grand Forks)","14th & Central","Sunshine Terrace","Campbell Library","Sacred Heart","Town Square Apartments","Mtc"]},{"bus_id":"5","From":"Mtc","To":"Mtc","S_No":"9","stop_id":["Mtc","N 5th St & 2nd Ave","7th & University","12th & University Wb","Salvation Army","20th & University","25th & University","Hamline & University","Christus Rex","Hancock/Bek","Wilkerson","State St./University","Tulane & University","Loaf N Jug","48th & University","N 51st St Shelter","N 51st St & 6th Ave Sb","N 53rd St & 6th Ave","West Walmart","N 53rd St & 10th Ave","N 51st St & 10th Ave","N 51st St & 6th Ave Eb","N 48th St & 6th Ave","Public Works","Gateway Terrace","Ramada","N 43rd St Shelter","N 43rd St & 6th Ave","N 42nd St & 6th Ave","Odegard Hall","University Place","Chester Fritz Auditorium","Johnstone/Gamble","Chester Fritz Library","Memorial Union","23rd & University","18th & University","15th & University","12th & University Eb","Ymca","Mtc"]},{"bus_id":"6","From":"Mtc","To":"Mtc","S_No":"11","stop_id":["Mtc","Cabela's","City Hall","10th & Central","Evergreen Estates","Egf Senior High","17th St & 4th Ave NW","17th St & 8th Ave NW","20th St & 7th Ave NW","20th St & 3rd Ave NW","Northland College","20th St & 5th Ave NE","17th St & 5th Ave NE","Fairfield Inn","Hugo's (East Grand Forks)","14th & Central","Sunshine Terrace","Campbell Library","River Cinema","Mtc"]},{"bus_id":"7","From":"Mtc","To":"Midtown","S_No":"13","stop_id":["Mtc","8th & Washington Sb","12th & Washington","15th & Washington","17th & Washington","Gf Library","Montessori School","S 17th St & 24th Ave Wb","S 20th St & 24th Ave Wb","S 23rd St & 24th Ave Wb","S 26th St & 24th Ave","Columbia Mall","S 31st St & 32nd Ave","Target","S 31st St","S 31st St & 36th Ave","36th Ave S","S Columbia Rd & 36th Ave","Development Homes","Walmart","Hugo's (32nd Ave S)","S 17th St & 28th Ave","S 17th St & 24th Ave Eb","S 17th St & 20th Ave","S 17th St & 17th Ave","Midtown"]},{"bus_id":"8","From":"Memorial Union","To":"Memorial Union","S_No":"15","stop_id":["Memorial Union","Altru Business Center","Dakota Boy's Ranch","S 20th St & 11th Ave","S 24th St & 11th Ave","Altru Columbia Rd","19th & Columbia","22nd & Columbia","S 26th St & 24th Ave","S 26th St & 26th Ave","Post Office","S 29th St & 32nd Ave","Columbia Mall","S 31st St & 32nd Ave","Target","S 38th St & 29th Ave","Linden Place","S 38th St & 24th Ave","S 34th St & 24th Ave","Primrose & 34th St","Century School Sb","Baron & 34th","S 34th St & 11th Ave","Garden View Drive","S 40th St & 11th Ave","Alerus Center","Odegard Hall","University Place","Chester Fritz Auditorium","Johnstone/Gamble","Chester Fritz Library","Memorial Union"]},{"bus_id":"9","From":"Hamline & University","To":"40th & Garden View","S_No":"17","stop_id":["Hamline & University","Christus Rex","Hancock/Bek","Wilkerson","Stanford Center","Lake Agassiz School","N 40th St & 6th Ave","Alerus Center","40th & Garden View"]},{"bus_id":"10","From":"Altru Professional Center","To":"Mtc 2","S_No":"19","stop_id":["Altru Professional Center","Curran Ct & 47th Ave","South Middle School","S 20th St & 43rd Ave","S 20th & 40th Ave","S 20th St & 36th Ave","Pembrooke Ct & 36th Ave","S Columbia Rd & 36th Ave","Columbia Mall","Walmart","Hugo's (32nd Ave S)","S 17th St & 28th Ave","S 17th St & 24th Ave Nb","S 17th St & 20th Ave","S 17th St & 17th Ave","Midtown","Hugo's (S Washington St)","Mcdonald's","8th & Washington Nb","Mtc 2"]},{"bus_id":"13","From":"Altru Columbia Rd","To":"Mtc","S_No":"21","stop_id":["Altru Columbia Rd","S 29th St & 17th Ave","Baron Blvd & 17th Ave","Century School Sb","S 34th St Sb","S 34th St & 24th Ave Sb","Columbia Mall","S 31st St & 32nd Ave","Target","Walmart","Hugo's (32nd Ave S)","S 17th St & 28th Ave","S 17th St & 24th Ave Nb","S 17th St & 20th Ave","S 17th St & 17th Ave","Midtown","Hugo's (S Washington St)","Mcdonald's","8th & Washington Nb","Mtc"]},{"bus_id":"UND-BLUE-ROUTE","From":"Do you work for CAT Bus?","To":"Do you work for CAT Bus?","S_No":"23","stop_id":["Do you work for CAT Bus?","Do you work for CAT Bus?"]},{"bus_id":"UND-NIGHT-ROUTE","From":"Do you work for CAT Bus?","To":"Do you work for CAT Bus?","S_No":"25","stop_id":["Do you work for CAT Bus?","Do you work for CAT Bus?"]},{"bus_id":"UND-PURPLE-ROUTE","From":"Do you work for CAT Bus?","To":"Do you work for CAT Bus?","S_No":"27","stop_id":["Do you work for CAT Bus?","Do you work for CAT Bus?"]},{"bus_id":"UND-RED-ROUTE","From":"Do you work for CAT Bus?","To":"Do you work for CAT Bus?","S_No":"29","stop_id":["Do you work for CAT Bus?","Do you work for CAT Bus?"]}]