[{"bus_id":"10","From":"Medcom St / Trident Medical Center","To":"Mary St / Meeting St","S_No":"1","stop_id":["Medcom St / Trident Medical Center","Hwy 78 / Shadow Ln","Hwy 78 / Fernwood Dr","Hwy 78 / Old University Blvd","Otranto Rd / Rivers Ave","S Antler Dr / Otranto Rd","S Antler Dr / Melnick Dr","Greenridge Rd / S Antler Dr","Greenridge Rd / Rivers Ave","Rivers Ave / Eagle Landing Blvd","Rivers Ave / Northwoods Blvd","Rivers Ave / Ashley Phosphate Rd","Rivers Ave / Morris Baker Blvd","Mabeline Rd / Trident Technical College","College Dr / Trident Technical College","Rivers Ave / Midland Park Rd","Rivers Ave / Eagle Dr","Hanahan Rd / Va Hospital","Hanahan Rd / Sc Works-Trident One Stop","Rivers Ave / Aichele Dr Sb","Rivers Ave / Aamaco Way","Rivers Ave / Benderson Dr","Rivers Ave / Aviation Ave","Rivers Ave / W. Oak Grove St","Rivers Ave / Remount Rd Sb","Rivers Ave / Sabal St","Rivers Ave / Taylor Street @ Rr Crossing","Rivers Ave / Target St","Rivers Ave / Rebecca St","Rivers Ave / Fuller St","Rivers Ave / Emden St Sb","Rivers Ave / Mall Dr","Rivers Ave / Rich St","Rivers Ave / Piggly Wiggly Dr","Rivers Ave / Meeting Street Rd","Rivers Ave / Macon Ave","Rivers Ave / Melbourne Ave","Rivers Ave / Helm Ave","Rivers Ave / Verde Ave","Rivers Ave / Shipwatch Square","Rivers Ave / Cosgrove Ave","Rivers Ave / Carver Ave","Rivers Ave / Success St","Military Magnet Academy","Carner Ave / Clement Ave","Meeting Street Rd / Hackemann Ave","Meeting Street Rd / Delaware Ave","Meeting St / Little Ave","Meeting St / Pittsburgh Ave","Meeting St / Four Mile Ln","Meeting St / Legacy Meats Sb","Meeting St / Greenleaf Rd","Meeting St / Cunnington St","Meeting St / Mt Pleasant St","Meeting St / Maple St","Meeting St / Romney St","Meeting St / Cool Blow St","Meeting St / Huger St","Meeting St / Johnson St Sb","Meeting St / Line St Sb","Meeting St / Spring St Sb","Meeting St / Mary St","Transit Mall","Mary St / Meeting St"]},{"bus_id":"11","From":"Centre Pointe Dr / Tanger Outlet Blvd (Northside)","To":"Mary St / Meeting St","S_No":"3","stop_id":["Centre Pointe Dr / Tanger Outlet Blvd (Northside)","Centre Pointe Dr / Wetland Crossing","Centre Pointe Dr / Golden Corral","International Blvd / I-526 Eb (Northside)","International Blvd / Boeing","Charleston International Airport","International Blvd / I-526e Entrance (Southside)","International Blvd / Darius Rucker Blvd","Emmett I. Davis Jr. Ave / Firestone Rd","W. Montague Ave / Calvin St","Montague Ave / Fargo St","Montague Ave / Dorchester Rd","Dorchester Rd / Paramount Dr","Dorchester Rd / Leeds Ave","Dorchester Rd / Leeds Ave Sb (At Shelter)","Dorchester Rd / Transfer St","Dorchester Rd / Lexington Ave Sb","Dorchester Rd / Bonds Ave Sb","Dorchester Rd / W Surrey Dr","Dorchester Rd / Stark Ln","Dorchester Rd / South Allen Dr","Dorchester Rd / Kent Ave","Dorchester Rd / Meeting Street Rd","Dorchester Rd / Pinehaven Dr","Rivers Ave / Cosgrove Ave","Reynolds Ave / N Atlantic Ave","Reynolds Ave / Spruill Ave","North Carolina Ave / Reynolds Ave","North Carolina Ave / Success St","North Carolina Ave / Calvert St","Spruill Ave / Baxter St","Spruill Ave / English St","Spruill Ave / Burton Ln","Spruill Ave / Stromboli Ave","Spruill Ave / Riverview Ave","Spruill Ave / Echo Ave","Spruill Ave / Groveland Ave","Spruill Ave / Little Ave","Meeting St / Pittsburgh Ave","Meeting St / Four Mile Ln","Meeting St / Legacy Meats Sb","Meeting St / Greenleaf Rd","Meeting St / Cunnington St","Morrison Dr / Meeting St","Morrison Dr / Brigade St","Morrison Dr / Romney St","Morrison Dr / Charleston County Magistrate Courts","Morrison Dr / Stuart St","Morrison Dr / Jackson St (Sanders-Clyde Elementary)","Columbus St / Drake St","Columbus St / America St","Meeting St / Spring St Sb","Meeting St / Mary St","Transit Mall","Mary St / Meeting St"]},{"bus_id":"12","From":"Otranto Rd / Rivers Ave","To":"N. Charleston Superstop on Cosgrove Ave","S_No":"5","stop_id":["Otranto Rd / Rivers Ave","S Antler Dr / Otranto Rd","S Antler Dr / Melnick Dr","Greenridge Rd / S Antler Dr","Greenridge Rd / Rivers Ave","Rivers Ave / Eagle Landing Blvd","Rivers Ave @ Bb&T","Northwoods Mall","Northwoods Blvd / Carolina Ice Palace","Northwoods Blvd / Lowes","Northwoods Blvd / Ashley Phosphate Rd","Ashley Phosphate Rd / Northside Dr","Ashley Phosphate Rd / Stall Rd","Ashley Phosphate Rd / N Spartan Blvd","Ashley Phosphate Rd / Pepperdam Ave","Ashley Phosphate Rd / Brandywine Rd","Ashley Phosphate Rd / Plantation Rd","Ashley Phosphate Rd / Pepperidge Dr","Ashley Phosphate Rd / Windsor Hill Dr","Ashley Phosphate Rd / Dorchester Manor Blvd","Ashley Phosphate Rd / Patriot Blvd","Ashley Phosphate Rd / Dorchester Rd","Dorchester Rd / Park Forest Pkwy","Dorchester Rd / Patriot Blvd Sb","Dorchester Rd / Archdale Blvd","Dorchester Rd / Parkgate Dr","Dorchester Rd / Foxwood Dr","Dorchester Rd / Forest Hills Dr","Dorchester Rd / Lowell Dr","Dorchester Rd / Cross County Rd","Dorchester Rd / Hunley Park","Dorchester Rd / Air Force Base Gate","Dorchester Rd / Lambs Rd","Dorchester Rd / Apartment Blvd","Dorchester Rd / Lake Ashley Park","Dorchester Rd / Hanniford Dr","Dorchester Rd / Great Oak Dr","Senior Center at Dorchester Road","Dorchester Rd / Michaux Pkwy","Dorchester Rd / Leslie St","Dorchester Rd / Gwinnett St","Dorchester Rd / Trailwood Dr","Dorchester Rd / Evanston Blvd","Dorchester Rd / Larchmont Dr","Dorchester Rd / Bon Aire Blvd","Dorchester Rd / Oak Ridge Plaza","Dorchester Rd / Montague Ave","Dorchester Rd / Paramount Dr","Dorchester Rd / Leeds Ave","Dorchester Rd / Leeds Ave Sb (At Shelter)","Dorchester Rd / Transfer St","Dorchester Rd / Lexington Ave Sb","Dorchester Rd / Bonds Ave Sb","Dorchester Rd / W Surrey Dr","Dorchester Rd / Stark Ln","Dorchester Rd / South Allen Dr","Dorchester Rd / Kent Ave","Dorchester Rd / Meeting Street Rd","Dorchester Rd / Pinehaven Dr","Rivers Ave / Commander Rd","N. Charleston Superstop on Cosgrove Ave"]},{"bus_id":"13","From":"Centre Pointe Dr / Tanger Outlet Blvd (Southside)","To":"N. Charleston Superstop","S_No":"7","stop_id":["Centre Pointe Dr / Tanger Outlet Blvd (Southside)","Tanger Outlet Blvd / Hotel Rd","Tanger Outlet Blvd / International Blvd","Emmett I. Davis Jr. Ave / Firestone Rd","W. Montague Ave / Banco Rd","Mall Dr / City Hall Ln","Mall Dr / Lacross Rd","Mall Dr / Rivers Ave","Rivers Ave / Rebecca St","Rivers Ave / Harley St","Rivers Ave / Renneau Ave","Casper Padgett Way / Remount Rd","Remount Rd / Craig Rd","Campbell St / Yeamans Hall Rd","Yeamans Hall Rd / Yeamans Hall Plaza","Remount Rd / Yeamans Hall Rd","Remount Rd / Leiderman St","Remount Rd / Attaway St","Remount Rd / Corner Ave","Remount Rd / Flanders Ave","Remount Rd / Saxon St","N Rhett Ave / Sumner Ave","N. Rhett Ave / Braddock Ave","N. Rhett Ave / Marquis Rd","Park Circle / E Montague Ave","Park Circle / S Rhett Ave","Park Circle / E Park Pl","Spruill Ave / Buist Ave","Spruill Ave / Bexley","Spruill Ave / Gullah Ave","Spruill Ave / Mcmillan Ave","Spruill Ave / Cosgrove Ave","Reynolds Ave / Florida Ave","N. Charleston Superstop"]},{"bus_id":"20","From":"King St / Mt. Pleasant St","To":"Meeting St / Chalmers St","S_No":"9","stop_id":["King St / Mt. Pleasant St","King St / Cypress St","King St / Poplar St","King St / Romney St","King St / Grove St","King St / Cleveland St","King St / Huger St","King St / Congress St","King St / Sumter St","King St / Engel St","King St / Line St","Columbus St / King St","Columbus St / Meeting St","Meeting St / Spring St Sb","Meeting St / Woolfe St","Meeting St / Mary St","Visitors Center / Charleston Museum","Meeting St / Burns Ln","Meeting St / Wentworth St","Meeting St / Market St","Meeting St / Cumberland St","Meeting St / Queen St","King St / Broad St","Meeting St / Chalmers St"]},{"bus_id":"30","From":"Mary St / Meeting St","To":"Citadel Mall","S_No":"11","stop_id":["Mary St / Meeting St","Meeting St / Woolfe St","Spring St / Meeting St","Spring St / King St","Spring St / Ashe St","Spring St / Rutledge Ave","Spring St / President St","Spring St / Hagood Ave","Savannah Hwy / Wesley Dr","Savannah Hwy / West Harrison Rd","Savannah Hwy / Parish Rd","Savannah Hwy / Blessed Sacrament School","Savannah Hwy / Avondale Ave","Savannah Hwy / Colyem Rd","Savannah Hwy / Apollo Rd","Savannah Hwy / West Oak Forest Dr","Savannah Hwy / Wateree Dr","Savannah Hwy / Briarcliff Dr","Savannah Hwy / Markfield Dr","Savannah Hwy / White Oak Dr","Savannah Hwy / Braxton Ave","Savannah Hwy / Wappoo Rd","Savannah Hwy / Dupont Rd","Savannah Hwy / Orleans Rd","Skylark Dr / Savannah Hwy (East Side)","Citadel Mall / S. Park Circle","Citadel Mall"]},{"bus_id":"31","From":"Mary St / Meeting St","To":"Sol Legare Rd / Folly Rd","S_No":"13","stop_id":["Mary St / Meeting St","Visitors Center / Charleston Museum","Meeting St / Calhoun St","Calhoun St / St Philip St","Calhoun St / Ashley Ave","Calhoun St / Jonathan Lucas St (Far Side)","Croghan Spur Rd / Fielding Connector","Albemarle Rd / Folly Rd Sb","Folly Road Blvd / Windermere Blvd","Folly Road Blvd / Formosa Dr","Folly Rd / Nashmor Rd","Folly Rd / Old Folly Rd Sb","Folly Rd / Carlin Ave","Folly Rd / Central Park Rd","Folly Rd / Ellis Oak Ave Sb","Folly Rd / Hunley Ave","Folly Rd / Eugene Gibbs St","Folly Rd / Camp Rd Sb","Folly Rd / Prescott St","Walmart @ Folly Rd","Folly Rd / Fort Johnson Rd","Fort Johnson Rd / Jeffords St","Fort Johnson Rd / Freer St","Fort Johnson Rd / Secessionville Rd","Secessionville  Rd / Sineca Pl","Secessionville Rd / Westchester Playground","Secessionville Rd / Westmoreland Ave","Secessionville Rd / Rainbow Rd","Secessionville Rd / Grimball Rd Ext","Grimball Rd Ext / Folly Rd","Sol Legare Rd / Folly Rd"]},{"bus_id":"32","From":"N. Charleston Superstop on Cosgrove Ave","To":"Bees Ferry Rd Walmart","S_No":"15","stop_id":["N. Charleston Superstop on Cosgrove Ave","Cosgrove Ave / Lenape St","Cosgrove Ave / Mott Ave","Sam Rittenberg Blvd / Durham Pl","Sam Rittenberg Blvd / Gamecock Ave","Sam Rittenberg Blvd / Amberly Rd","Sam Rittenberg Blvd / Dickens St","Sam Rittenberg Blvd / Downing St","Sam Rittenberg Blvd / Ashley Hall Rd","Sam Rittenberg Blvd / N. Woodmere Dr","Sam Rittenberg Blvd / Ashley River Rd","Sam Rittenberg Blvd / Outback Plaza","Sam Rittenberg Blvd / Colonial Village Apts","Sam Rittenberg Blvd / Orleans Rd","Citadel Mall","Skylark Dr / Savannah Hwy - (Westside)","Hwy 17 / Ashley Town Center Rd","Savannah Hwy / Parkdale Dr","Savage Rd / Etiwan Ave","Castlewood Dr / Savage Rd","Castlewood Blvd / Sir Scott Pl","Savage Rd / Castlewood Blvd","Henry Tecklenburg Dr @ Charleston Ent","Henry Tecklenburg Dr / Watchtower Ln","Bon Secours-St Francis Hospital","Glenn Mcconnell Pkwy / Bairds Cove","Glenn Mcconnell Pkwy / Mary Ader Ave","Glenn Mcconnell Pkwy / Goodwill Way","Bees Ferry Rd Walmart"]},{"bus_id":"33","From":"Ashley River Rd / Bees Ferry Rd","To":"Mary St / Meeting St","S_No":"17","stop_id":["Ashley River Rd / Bees Ferry Rd","Ashley River Rd / Glendale Dr","Ashley River Rd / Plainview Rd Eb","Ashley River Rd / Old Parsonage Rd","Ashley River Rd / Woodland Rd","Ashley River Rd / Dogwood Rd","Ashley River Rd / Magwood Dr","Ashley River Rd / Sledge Ln","Ashley River Rd / Planters Trace Apartments","Ashley River Rd / Ashley Hall Plantation Rd","Ashley River Rd / Richmond St","Ashley River Rd / Tobias Gadson Blvd","Tobias Gadsden Blvd / Paul Cantrell Blvd Sb","Orleans Rd / Carrie St","Orleans Road / Carverwood Ln","Citadel Mall","Sam Rittenberg Blvd / Orleans Rd","Sam Rittenberg Blvd / Plugs Appliance Store","Sam Rittenberg Blvd / Ashley River Rd","Hwy 61 / Wappoo Rd","Hwy 61 / Crull Dr","Hwy 61 / Spanish Oaks Apartments","Ashley River Rd / Brookwood Cir","Ashley River Rd / Playground Rd","Ashley River Rd / Carriage Ln","St. Andrews Blvd / Davidson Ave","St Andrews Blvd / Sycamore Ave","St Andrews Blvd / Avondale Ave","Hwy 61 / Oakdale Pl","St. Andrews Blvd / Riverdale Dr","Hwy 61 / Parish Rd","Hwy 61 / West Harrison Rd","Fielding Connector / Ripley Point Dr","Calhoun St / Courtenay Dr","Calhoun St / Jonathan Lucas St (Near Side)","Calhoun St / Ashley Ave (Farside)","Calhoun St / St Philip St","Transit Mall","Mary St / Meeting St"]},{"bus_id":"40","From":"Mary St / Meeting St","To":"Walmart - Market at Oakland (Park & Ride)","S_No":"19","stop_id":["Mary St / Meeting St","Meeting St / Woolfe St","Meeting St / Line St Nb","Meeting St / Sheppard St","Meeting St / Johnson St Nb","Coleman Blvd / Patriots Point Blvd","Houston Northcutt Blvd / Harbor Pointe Dr","Houston Northcutt Blvd / Ann Edwards Ln","Johnnie Dodds Blvd (Frontage Rd) / Lansing Dr","Johnnie Dodds Blvd (Frontage Rd) / Cottingham Dr","Johnnie Dodds Blvd (Frontage Rd) / S Shelmore Blvd","Johnnie Dodds Blvd (Frontage Rd) / Dragoon Dr","Johnnie Dodds Blvd (Frontage Rd) / Anna Knapp Blvd","Anna Knapp Blvd / Johnnie Dodds Blvd (N Of 17)","Johnnie Dodds Blvd / Bowman Rd (N Of 17)","Bowman Rd / Rosemead Rd","Stuart Engals Blvd / Bowman Rd","Stuart Engals Blvd / Wando Crossing Center (Park & Ride)","Hwy 17 / Freeman Scott Rd","Hwy 17 / Venning Rd","Hwy 17 N  / Market Center Blvd","Towne Centre / Market Center Blvd","Hungry Neck Blvd / Theater Dr","Sweetgrass Basket Pkwy / Two Island Ct","Sweetgrass Basket Pkwy / Basketweave Dr","Six Mile Rd / Tea Planter Ln","Hwy 17 / Long Point Rd","Hwy 17 / Hamlin Rd","Hwy 17 / Hwy 41","Walmart - Market at Oakland (Park & Ride)"]},{"bus_id":"41","From":"Stuart Engals Blvd / Wando Crossing Center (Park & Ride)","To":"Mary St / Meeting St","S_No":"21","stop_id":["Stuart Engals Blvd / Wando Crossing Center (Park & Ride)","Midtown Ave / Musc Health East Cooper","Watermark Rd / Appling Dr","Chuck Dawley Blvd / Old Georgetown Rd","Myrick Rd / Chuck Dawley Blvd","Rifle Range Rd / Cassidy Ct","Coleman Blvd / Sea Island Shopping Center","Coleman Blvd / Brookgreen Town Center","Coleman / Moultrie Middle School","Coleman Blvd / Simmons St","Coleman Blvd / Mill St Wb","Coleman Blvd / Pelzer Dr","Coleman Blvd / Provincial Circle","Houston Northcutt Blvd / Harbor Pointe Dr","Houston Northcutt Blvd / Ann Edwards Ln","Wingo Way / Sandpiper Dr Wb","Wingo Way / Cooper River Dr","Mt Pleasant Waterfront Park","Harry Hallman Blvd / Patriots Point Rd","Patriots Point Blvd / Coleman Blvd","Morrison Dr / Stuart St","Morrison Dr / Jackson St (Sanders-Clyde Elementary)","Columbus St / Drake St","Columbus St / America St","Meeting St / Spring St Sb","Meeting St / Woolfe St","Meeting St / Mary St","Transit Mall","Mary St / Meeting St"]},{"bus_id":"42","From":"Wando High School","To":"Hungry Neck Blvd / Theater Dr","S_No":"23","stop_id":["Wando High School","Carolina Park Blvd / Hwy 17","Mt Pleasant Hospital","Hwy 17 / Park West","Hwy 17 / Lexington Dr","Hwy 17 / Hwy 41","Hwy 17 / Brickyard Pkwy","Hwy 17 / Long Point Rd","Six Mile Rd / Tea Planter Ln","Sweetgrass Basket Pkwy / Basketweave Dr","Sweetgrass Basket Pkwy / Two Island Ct","Hungry Neck Blvd / Theater Dr"]},{"bus_id":"102","From":"N. Charleston Superstop","To":"Calhoun St / Ashley Ave","S_No":"25","stop_id":["N. Charleston Superstop","Cosgrove Ave / Lenape St","Cosgrove Ave / Mott Ave","Azalea Dr / Meridian Rd","Azalea Dr / Elegans Dr","Azalea Dr / Baker Hospital Blvd","Baker Hospital Blvd / Evatt Ln","King St Ext / Lanxess Chemical Dr","Austin Ave / Peace St","Austin Ave / Peonie St","Freddie Whaley Community Center Sb","King St / Ashepoo Ln","King St / Heriot St","King St / Mt. Pleasant St","Mt Pleasant St / King St","Mt Pleasant St / Rutledge Ave","Rutledge Ave / Sans Souci St","Rutledge Ave / Maple St","Rutledge Ave / Simons St","Rutledge Ave / Grove St","Rutledge Ave / Moultrie St","Moultrie St / Ashley Ave","Elmwood Ave / Moultrie St","Elmwood Ave / Congress St","Sumter St / President St","Sumter St / Ashley Ave","Sumter St / Rutledge Ave","Rutledge Ave / Fishburne Ave","Rutledge Ave / Line St","Rutledge Ave / Spring St","Rutledge Ave / Bee St","Rutledge Ave / Vanderhorst St","Calhoun St / Ashley Ave"]},{"bus_id":"103","From":"Dorchester Rd / Paramount Dr","To":"N. Charleston Superstop on Cosgrove Ave","S_No":"27","stop_id":["Dorchester Rd / Paramount Dr","Dorchester Rd / Leeds Ave","Leeds Ave / Spur St","Leeds Ave / Primrose Ave","Martha Dr / Peacock Ave","Martha Dr / Budds Ave","Martha Dr / Stith Ave","Martha Dr / Ranger Dr","Ranger Dr / Lawrence St","Lawrence St / Constitution Ave","Constitution Ave / Ranger Dr","Dorchester Rd / Stark Ln","Dorchester Rd / South Allen Dr","Dorchester Rd / Kent Ave","Dorchester Rd / Meeting Street Rd","Dorchester Rd / Pinehaven Dr","Rivers Ave / Commander Rd","N. Charleston Superstop on Cosgrove Ave"]},{"bus_id":"104","From":"Centre Pointe Dr / Tanger Outlet Blvd (Northside)","To":"N. Charleston Superstop on Cosgrove Ave","S_No":"29","stop_id":["Centre Pointe Dr / Tanger Outlet Blvd (Northside)","Centre Pointe Dr / Wetland Crossing","Centre Pointe Dr / Golden Corral","Emmett I. Davis Jr. Ave / Firestone Rd","W. Montague Ave / Banco Rd","Mall Dr / City Hall Ln","Mall Dr / Lacross Rd","Rivers Ave / Mall Dr","Rivers Ave / Rich St","North Charleston Transit Center","Durant Ave / Bexley St","Durant Ave / Bixby Ln","Mixson Ave / E Montague Ave","Montague Ave / Marlboro Rd","Montague Ave / Park Place West","Park Circle / S Rhett Ave","Park Circle / E Park Pl","Montague Ave / Spruill Ave","Montague Ave / Jenkins Ave","Montague Ave / O'Hear Ave","Virginia Ave / Bethany St","Noisette Blvd / 2nd St N","Turnbull Ave / Manley Ave","Mcmillan Ave / Hobson Ave","Mcmillan Ave / St John St","Mcmillan Ave / Old Pine Circle E","N. Charleston Superstop on Cosgrove Ave"]},{"bus_id":"203","From":"Fishburne St / Horizon St Park & Ride","To":"Fishburne St / Horizon St Park & Ride","S_No":"31","stop_id":["Fishburne St / Horizon St Park & Ride","Horizon St / Medical Park & Ride","Harborview Tower","Courtenay Dr / Charleston Center Dr","Jonathan Lucas St / Musc Quad","President St / Bee St","Fishburne St / Horizon St Park & Ride"]},{"bus_id":"210","From":"Aquarium (Concord St)","To":"Aquarium (Concord St)","S_No":"33","stop_id":["Aquarium (Concord St)","Calhoun St / East Bay St","Calhoun St / Elizabeth St","Calhoun St / Meeting St (Near Side)","Visitors Center on John St","Warren St / St Philip St","St Philip St / Calhoun St","St Philip St / Liberty St","Wentworth St / Coming St","Coming St / George St","Calhoun St / St Philip St","Calhoun St / King St","Calhoun St / Meeting St (Far Side)","Calhoun St / Elizabeth St","Aquarium (Concord St)"]},{"bus_id":"211","From":"Visitors Center on John St","To":"Visitors Center on John St","S_No":"35","stop_id":["Visitors Center on John St","King St / Vanderhorst St","King St / Calhoun St","King St / George St","King St / Wentworth St","King St / Market St","King St / Clifford St","King St / Queen St","Broad St / Meeting St","Broad St / Church St","E Bay St / N Atlantic Wharf","Waterfront Park","Concord St / Cumberland St","Market St / East Bay St","Market St / Meeting St","Meeting St / Hasell St","Meeting St / George St","Meeting St / Calhoun St","Meeting St / Charlotte St","Charleston Museum / Visitors Center","Meeting St / Mary St","Meeting St / Woolfe St","Spring St / Meeting St","King St / Cannon St","King St / Morris St","Visitors Center on John St"]},{"bus_id":"213","From":"Mary St / Meeting St","To":"Mary St / Meeting St","S_No":"37","stop_id":["Mary St / Meeting St","Mary St / America St","America St / Reid St","America St / Columbus St","Meeting St / Spring St Sb","Meeting St / Mary St","Visitors Center on John St","King St / Vanderhorst St","Calhoun St / St Philip St","Calhoun St / Smith St","Calhoun St / Ashley Ave","Calhoun St / Jonathan Lucas St (Far Side)","Courtenay Dr / Doughty St","Bee St / Va Hospital","Lockwood Dr / Westedge St","Lockwood Dr / Brittlebank Park","Fishburne St / Horizon St","Fishburne St / Burke High School","President St / Line St","Cannon St / President St","Cannon St / Rutledge Ave","Cannon St / Coming St","Cannon St / St Philip St","Mary St / Meeting St"]},{"bus_id":"301","From":"Citadel Mall","To":"Bees Ferry Rd Walmart","S_No":"39","stop_id":["Citadel Mall","Skylark Dr / Savannah Hwy - (Westside)","Hwy 17 / Ashley Town Center Rd","Savannah Hwy / Parkdale Dr","Savage Rd / Etiwan Ave","Castlewood Dr / Savage Rd","Castlewood Blvd / Sir Scott Pl","Savage Rd / Castlewood Blvd","Henry Tecklenburg Dr @ Charleston Ent","Henry Tecklenburg Dr / Watchtower Ln","Bon Secours-St Francis Hospital","Magwood Dr / Ashley Crossing Plaza","Charlie Hall Blvd / Magwood Dr","Charlie Hall Blvd / Medical Park","Charlie Hall Blvd / Charleston Dorchester Mental Health Center","Glenn Mcconnell Pkwy / Bairds Cove","Glenn Mcconnell Pkwy / Mary Ader Ave","Glenn Mcconnell Pkwy / Goodwill Way","Bees Ferry Rd Walmart"]},{"bus_id":"BEACH_REACH_SHUTTLE","From":"Ocean Blvd / 14th Ave","To":"Towne Centre / Market Center Blvd","S_No":"41","stop_id":["Ocean Blvd / 14th Ave","Hungry Neck Blvd / Theater Dr","Towne Centre / Market Center Blvd"]},{"bus_id":"XP1","From":"Rivers Ave Park & Ride Bay 1","To":"James Island Walmart (Park & Ride)","S_No":"43","stop_id":["Rivers Ave Park & Ride Bay 1","Meeting St / Spring St Sb","Visitors Center / Charleston Museum","Calhoun St / St Philip St","Calhoun St / Ashley Ave","Calhoun St / Jonathan Lucas St (Far Side)","James Island Walmart (Park & Ride)"]},{"bus_id":"XP2","From":"Citadel Mall","To":"Walmart - Market at Oakland (Park & Ride)","S_No":"45","stop_id":["Citadel Mall","Calhoun St / Jonathan Lucas St (Near Side)","Calhoun St / Ashley Ave (Farside)","Calhoun St / St Philip St","Charleston Museum / Visitors Center","Meeting St / Columbus St","Stuart Engals Blvd / Wando Crossing Center (Park & Ride)","Walmart - Market at Oakland (Park & Ride)"]},{"bus_id":"XP3","From":"Dorchester Village Shopping Center Park & Ride","To":"Calhoun St / Jonathan Lucas St (Far Side)","S_No":"47","stop_id":["Dorchester Village Shopping Center Park & Ride","Festival Centre Park & Ride","Dorchester Rd / Air Force Base Gate","Fuel Farm Rd / Dreamliner Dr","Dreamliner Dr / Boeing","Meeting St / Spring St Sb","Visitors Center / Charleston Museum","Calhoun St / St Philip St","Calhoun St / Ashley Ave","Calhoun St / Jonathan Lucas St (Far Side)"]}]